dataplane/__init__.py
dataplane/hello.py
dataplane/DataStorage/s3/__init__.py
dataplane/DataStorage/s3/s3_download.py
dataplane/DataStorage/s3/s3_upload.py
dataplane/DataStorage/s3/test_s3.py
dataplane/DataStorage/s3/test_s3_object.py
dataplane/Microsoft/__init__.py
dataplane/Microsoft/Sharepoint/__init__.py
dataplane/Microsoft/Sharepoint/sharepoint_download.py
dataplane/Microsoft/Sharepoint/sharepoint_upload.py
dataplane/Microsoft/Sharepoint/test_sharepoint.py
dataplane/Microsoft/Sharepoint/test_sharepoint_nonroot.py
dataplane/Microsoft/Sharepoint/test_sharepoint_object.py
dataplane/Microsoft/Teams/__init__.py
dataplane/Microsoft/Teams/test_webhook_send.py
dataplane/Microsoft/Teams/webhook_send.py
dataplane/pipelinerun/__init__.py
dataplane/pipelinerun/data_persist/__init__.py
dataplane/pipelinerun/data_persist/pandas_redis_store.py
dataplane/pipelinerun/data_persist/pandas_s3_store.py
dataplane/pipelinerun/data_persist/redis_store.py
dataplane/pipelinerun/data_persist/test_pandas_redis.py
dataplane/pipelinerun/data_persist/test_redis.py
dataplane/pipelinerun/data_persist/test_s3_store.py
dataplane-0.1.2.dist-info/LICENSE
dataplane-0.1.2.dist-info/METADATA
dataplane-0.1.2.dist-info/WHEEL
dataplane-0.1.2.dist-info/top_level.txt
dataplane-0.1.2.dist-info/RECORD
