Metadata-Version: 2.1
Name: dataplane
Version: 0.1.2
Summary: The data engineering library to build robust, reliable and on time data pipelines in Python.
Author: Saul Frank, Dataplane, Inc.
Project-URL: Homepage, https://dataplane.app
Project-URL: Github, https://github.com/dataplane-app/dataplane-python-package
Project-URL: Issues, https://github.com/dataplane-app/dataplane/issues
Project-URL: Feedback, https://github.com/dataplane-app/dataplane/discussions
Keywords: workflow,data-science,data,airflow,etl,dataplane,data-engineering,data-pipelines,datawarehouse,automation,data-analysis,scheduler
Classifier: Programming Language :: Python :: 3
Classifier: License :: OSI Approved :: BSD License
Classifier: Operating System :: OS Independent
Requires-Python: >=3.7
License-File: LICENSE
